georss_emsc_csem_earthquakes_client/__init__.py
georss_emsc_csem_earthquakes_client-0.3.dist-info/LICENSE
georss_emsc_csem_earthquakes_client-0.3.dist-info/METADATA
georss_emsc_csem_earthquakes_client-0.3.dist-info/WHEEL
georss_emsc_csem_earthquakes_client-0.3.dist-info/top_level.txt
georss_emsc_csem_earthquakes_client-0.3.dist-info/RECORD
