Metadata-Version: 2.1
Name: georss-emsc-csem-earthquakes-client
Version: 0.3
Summary: A GeoRSS client library for the EMSC CSEM Earthquakes feed.
Home-page: https://github.com/msekoranja/python-georss-emsc-csem-earthquakes-client
Author: Matej Sekoranja
Author-email: matej.sekoranja@gmail.com
License: UNKNOWN
Platform: UNKNOWN
Classifier: Programming Language :: Python :: 3.6
Classifier: Programming Language :: Python :: 3.7
Classifier: Programming Language :: Python :: 3.8
Classifier: License :: OSI Approved :: Apache Software License
Classifier: Operating System :: OS Independent
Requires-Dist: georss-client (>=0.12)
